mycalc/calculator.py
MyPack1024-0.0.1.dist-info/METADATA
MyPack1024-0.0.1.dist-info/WHEEL
MyPack1024-0.0.1.dist-info/top_level.txt
MyPack1024-0.0.1.dist-info/RECORD
